pyos/__init__.py
pyos/builder.py
pyos/cli.py
pyos/emulator.py
pyos/kernel.py
pyos/boot/__init__.py
pyos/boot/bootloader.asm
pyos/compiler/__init__.py
pyos/compiler/assembler.py
pyos/compiler/codegen.py
pyos/drivers/__init__.py
pyos/drivers/keyboard.py
pyos/drivers/screen.py
pyos/interrupts/__init__.py
pyos/interrupts/handler.py
pyos/interrupts/idt.py
pyos/memory/__init__.py
pyos/memory/gdt.py
pyos/memory/manager.py
pyos/syscalls/__init__.py
pyos/syscalls/handler.py
pyos_kernel-0.1.0.dist-info/licenses/LICENSE
pyos_kernel-0.1.0.dist-info/METADATA
pyos_kernel-0.1.0.dist-info/WHEEL
pyos_kernel-0.1.0.dist-info/entry_points.txt
pyos_kernel-0.1.0.dist-info/top_level.txt
pyos_kernel-0.1.0.dist-info/RECORD
