Metadata-Version: 2.4
Name: pyOS-kernel
Version: 0.1.0
Summary: Build complete operating systems using Python - compiles to Assembly and Machine Code
Author-email: i87kxxz <i87kxxz@users.noreply.github.com>
Maintainer-email: i87kxxz <i87kxxz@users.noreply.github.com>
License: MIT
Project-URL: Homepage, https://github.com/i87kxxz/pyOS
Project-URL: Documentation, https://github.com/i87kxxz/pyOS#readme
Project-URL: Repository, https://github.com/i87kxxz/pyOS
Project-URL: Issues, https://github.com/i87kxxz/pyOS/issues
Keywords: operating-system,os,kernel,assembly,x86,bootloader,low-level,systems-programming,qemu,nasm
Classifier: Development Status :: 4 - Beta
Classifier: Intended Audience :: Developers
Classifier: Intended Audience :: Education
Classifier: License :: OSI Approved :: MIT License
Classifier: Operating System :: OS Independent
Classifier: Programming Language :: Python :: 3
Classifier: Programming Language :: Python :: 3.8
Classifier: Programming Language :: Python :: 3.9
Classifier: Programming Language :: Python :: 3.10
Classifier: Programming Language :: Python :: 3.11
Classifier: Programming Language :: Python :: 3.12
Classifier: Programming Language :: Assembly
Classifier: Topic :: Software Development :: Compilers
Classifier: Topic :: System :: Operating System Kernels
Classifier: Topic :: Education
Requires-Python: >=3.8
License-File: LICENSE
Requires-Dist: click>=8.0.0
Provides-Extra: dev
Requires-Dist: pytest>=7.0.0; extra == "dev"
Requires-Dist: black>=23.0.0; extra == "dev"
Requires-Dist: flake8>=6.0.0; extra == "dev"
Dynamic: license-file
